tests/__init__.py
tests/test_parsing.py
tests/test_utils.py
tests/test_visualisation.py
wardley_map/__init__.py
wardley_map/create_wardley_map.py
wardley_map/wardley_maps.py
wardley_map/wardley_maps_utils.py
wardleymap-0.2.1.dist-info/licenses/LICENSE
wardleymap-0.2.1.dist-info/METADATA
wardleymap-0.2.1.dist-info/WHEEL
wardleymap-0.2.1.dist-info/top_level.txt
wardleymap-0.2.1.dist-info/RECORD
