Metadata-Version: 2.4
Name: wardleymap
Version: 0.2.1
Summary: A Python package to create and visualise Wardley Maps
Home-page: https://wardleymaps.ai/
Author: Mark Craddock
Author-email: wardley@firstliot.uk
Classifier: Programming Language :: Python :: 3
Classifier: License :: OSI Approved :: MIT License
Classifier: Operating System :: OS Independent
Requires-Python: >=3.6
License-File: LICENSE
Requires-Dist: matplotlib
Requires-Dist: pyvis
Requires-Dist: networkx
Requires-Dist: toml
Requires-Dist: werkzeug
Requires-Dist: pyyaml
Dynamic: author
Dynamic: author-email
Dynamic: classifier
Dynamic: description
Dynamic: description-content-type
Dynamic: home-page
Dynamic: license-file
Dynamic: requires-dist
Dynamic: requires-python
Dynamic: summary
